MANIFEST.in
partner_view.xml
pricelist_view.xml
product_data.xml
product_demo.xml
product_image_demo.xml
product_pricelist_demo.yml
product_report.xml
product_shortcut_data.xml
product_view.xml
setup.py
./__init__.py
./__openerp__.py
./_common.py
./partner.py
./pricelist.py
./product.py
./report/__init__.py
./report/pricelist.py
./report/product_pricelist.py
./wizard/__init__.py
./wizard/product_price.py
i18n/am.po
i18n/ar.po
i18n/bg.po
i18n/bs.po
i18n/ca.po
i18n/cs.po
i18n/da.po
i18n/de.po
i18n/el.po
i18n/es.po
i18n/es_AR.po
i18n/es_CL.po
i18n/es_CR.po
i18n/es_EC.po
i18n/es_MX.po
i18n/es_PY.po
i18n/es_VE.po
i18n/et.po
i18n/eu.po
i18n/fi.po
i18n/fr.po
i18n/gl.po
i18n/hr.po
i18n/hu.po
i18n/id.po
i18n/it.po
i18n/ja.po
i18n/ko.po
i18n/lo.po
i18n/lt.po
i18n/lv.po
i18n/mk.po
i18n/mn.po
i18n/nb.po
i18n/nb_NB.po
i18n/nl.po
i18n/nl_BE.po
i18n/pl.po
i18n/product.pot
i18n/pt.po
i18n/pt_BR.po
i18n/ro.po
i18n/ru.po
i18n/sk.po
i18n/sl.po
i18n/sq.po
i18n/sr.po
i18n/sr@latin.po
i18n/sv.po
i18n/th.po
i18n/tlh.po
i18n/tr.po
i18n/uk.po
i18n/vi.po
i18n/zh_CN.po
i18n/zh_TW.po
images/product.png
images/product_pricelists.jpeg
images/product_uom.jpeg
images/products_categories.jpeg
images/products_form.jpeg
openerp_product.egg-info/PKG-INFO
openerp_product.egg-info/SOURCES.txt
openerp_product.egg-info/dependency_links.txt
openerp_product.egg-info/requires.txt
openerp_product.egg-info/top_level.txt
process/product_process.xml
report/product_label.xml
report/product_label.xsl
report/product_price.xsl
report/product_pricelist.rml
report/product_pricelist.sxw
security/ir.model.access.csv
security/product_security.xml
test/product_pricelist.yml
test/product_uom.yml
wizard/product_price_view.xml